regulAS/__init__.py
regulAS/app.py
regulAS/conf/default.yaml
regulAS/core/__init__.py
regulAS/core/regulas.py
regulAS/persistence/__init__.py
regulAS/persistence/dao.py
regulAS/reports/__init__.py
regulAS/reports/base.py
regulAS/reports/export_textual.py
regulAS/reports/export_visual.py
regulAS/reports/export_visual_vis.py
regulAS/reports/performance.py
regulAS/reports/ranking.py
regulAS/utils/__init__.py
regulAS/utils/base.py
regulAS/utils/loader.py
regulAS-2023.7.1.dist-info/LICENSE
regulAS-2023.7.1.dist-info/METADATA
regulAS-2023.7.1.dist-info/WHEEL
regulAS-2023.7.1.dist-info/top_level.txt
regulAS-2023.7.1.dist-info/RECORD
